silenceofthelambs/__init__.py
silenceofthelambs/auto.py
silenceofthelambs/main.py
silenceofthelambs-0.0.2.dist-info/LICENSE
silenceofthelambs-0.0.2.dist-info/METADATA
silenceofthelambs-0.0.2.dist-info/WHEEL
silenceofthelambs-0.0.2.dist-info/top_level.txt
silenceofthelambs-0.0.2.dist-info/RECORD
