Metadata-Version: 2.1
Name: silenceofthelambs
Version: 0.0.2
Summary: Decrypt shush-like KMS-encrypted strings stored in the environment
Home-page: UNKNOWN
Author: Sam Jarrett
Author-email: sam@samjarrett.com.au
License: MIT
Platform: UNKNOWN
Classifier: License :: OSI Approved :: MIT License
Classifier: Programming Language :: Python
Classifier: Programming Language :: Python :: 3
Classifier: Programming Language :: Python :: 3.6
Classifier: Programming Language :: Python :: 3.7
Classifier: Programming Language :: Python :: 3.8
Classifier: Programming Language :: Python :: 3.9
Provides-Extra: with_boto3
Requires-Dist: boto3 (>=1.17.0) ; extra == 'with_boto3'
